agrihealth/__init__.py
agrihealth/agrihealth.py
agrihealth/common.py
agrihealth/core/__init__.py
agrihealth/core/foliummap.py
agrihealth/core/imageoverlay.py
agrihealth/core/leafletmap.py
agrihealth/core/shapefilehandler.py
agrihealth/core/tiffhandler.py
agrihealth/core/videooverlay.py
agrihealth/core/wmslayer.py
agrihealth-0.0.3.dist-info/licenses/LICENSE
agrihealth-0.0.3.dist-info/METADATA
agrihealth-0.0.3.dist-info/WHEEL
agrihealth-0.0.3.dist-info/entry_points.txt
agrihealth-0.0.3.dist-info/top_level.txt
agrihealth-0.0.3.dist-info/RECORD
