Metadata-Version: 2.4
Name: agrihealth
Version: 0.0.3
Summary: agrihealth is a Python demo package for sustainable agriculture.
Home-page: https://github.com/terra-geo/agrihealth
Author: Your Name
Author-email: M Fisher <climatealerta@gmail.com>
License: MIT License
Project-URL: Homepage, https://github.com/terra-geo/agrihealth
Keywords: agrihealth
Classifier: Intended Audience :: Developers
Classifier: License :: OSI Approved :: MIT License
Classifier: Natural Language :: English
Classifier: Programming Language :: Python :: 3.8
Classifier: Programming Language :: Python :: 3.9
Classifier: Programming Language :: Python :: 3.10
Classifier: Programming Language :: Python :: 3.11
Classifier: Programming Language :: Python :: 3.12
Requires-Python: >=3.8
License-File: LICENSE
Requires-Dist: numpy
Requires-Dist: folium
Requires-Dist: ipyleaflet
Requires-Dist: geopandas
Requires-Dist: ipywidgets
Requires-Dist: seaborn
Requires-Dist: matplotlib
Requires-Dist: rasterstats
Requires-Dist: pyproj
Requires-Dist: rasterio
Requires-Dist: branca
Provides-Extra: all
Requires-Dist: agrihealth[extra]; extra == "all"
Provides-Extra: extra
Requires-Dist: pandas; extra == "extra"
Dynamic: author
Dynamic: home-page
Dynamic: license-file
Dynamic: requires-python
